drb/drivers/file/__init__.py
drb/drivers/file/_version.py
drb/drivers/file/file.py
drb/exceptions/file.py
drb/topics/file/__init__.py
drb/topics/file/cortex.yml
drb_driver_file-1.1.0.data/data/requirements.txt
drb_driver_file-1.1.0.dist-info/METADATA
drb_driver_file-1.1.0.dist-info/WHEEL
drb_driver_file-1.1.0.dist-info/entry_points.txt
drb_driver_file-1.1.0.dist-info/top_level.txt
drb_driver_file-1.1.0.dist-info/RECORD
