Metadata-Version: 2.1
Name: drb-driver-file
Version: 1.1.0
Summary: DRB File implementation
Home-page: https://gitlab.com/drb-python/impl/file
Author: GAEL Systems
Author-email: drb-python@gael.fr
License: UNKNOWN
Project-URL: Documentation, https://drb-python.gitlab.io/impl/file
Project-URL: Source, https://gitlab.com/drb-python/impl/file
Platform: UNKNOWN
Classifier: Programming Language :: Python :: 3.8
Classifier: License :: OSI Approved :: Apache Software License
Classifier: Operating System :: OS Independent
Requires-Python: >=3.8
Requires-Dist: drb (~=2.0.0)
